CHANGELOG.md
MANIFEST.in
README.md
pyproject.toml
requirements.txt
setup.py
sourcedefender.egg-info/PKG-INFO
sourcedefender.egg-info/SOURCES.txt
sourcedefender.egg-info/dependency_links.txt
sourcedefender.egg-info/entry_points.txt
sourcedefender.egg-info/not-zip-safe
sourcedefender.egg-info/requires.txt
sourcedefender.egg-info/top_level.txt
src/CHANGELOG.md
src/__init__.py
src/__main__.py
src/engine.cpython-312-x86_64-linux-gnu.so
src/hook-sourcedefender.py
src/ext/darwin/universal/64/310/engine.cpython-310-darwin.so
src/ext/darwin/universal/64/311/engine.cpython-311-darwin.so
src/ext/darwin/universal/64/312/engine.cpython-312-darwin.so
src/ext/darwin/universal/64/313/engine.cpython-313-darwin.so
src/ext/darwin/universal/64/314/engine.cpython-314-darwin.so
src/ext/linux/aarch64/64/310/engine.cpython-310-aarch64-linux-gnu.so
src/ext/linux/aarch64/64/311/engine.cpython-311-aarch64-linux-gnu.so
src/ext/linux/aarch64/64/312/engine.cpython-312-aarch64-linux-gnu.so
src/ext/linux/aarch64/64/313/engine.cpython-313-aarch64-linux-gnu.so
src/ext/linux/aarch64/64/314/engine.cpython-314-aarch64-linux-gnu.so
src/ext/linux/x86_64/64/310/engine.cpython-310-x86_64-linux-gnu.so
src/ext/linux/x86_64/64/311/engine.cpython-311-x86_64-linux-gnu.so
src/ext/linux/x86_64/64/312/engine.cpython-312-x86_64-linux-gnu.so
src/ext/linux/x86_64/64/313/engine.cpython-313-x86_64-linux-gnu.so
src/ext/linux/x86_64/64/314/engine.cpython-314-x86_64-linux-gnu.so
src/ext/windows/amd64/64/310/engine.cp310-win_amd64.pyd
src/ext/windows/amd64/64/311/engine.cp311-win_amd64.pyd
src/ext/windows/amd64/64/312/engine.cp312-win_amd64.pyd
src/ext/windows/amd64/64/313/engine.cp313-win_amd64.pyd
src/ext/windows/amd64/64/314/engine.cp314-win_amd64.pyd