Metadata-Version: 2.4
Name: sourcedefender
Version: 16.0.41
Summary: Advanced encryption protecting your python codebase.
Home-page: https://sourcedefender.co.uk/?src=pypi-url
Author: SOURCEdefender
Author-email: hello@sourcedefender.co.uk
License: Proprietary
Project-URL: Dashboard, https://dashboard.sourcedefender.co.uk/login?src=pypi-navbar
Keywords: encryption source aes
Classifier: Development Status :: 5 - Production/Stable
Classifier: Intended Audience :: Developers
Classifier: Intended Audience :: Education
Classifier: Intended Audience :: Information Technology
Classifier: Intended Audience :: Other Audience
Classifier: Intended Audience :: Science/Research
Classifier: Intended Audience :: System Administrators
Classifier: Topic :: Security
Classifier: Topic :: Security :: Cryptography
Classifier: Topic :: Software Development
Classifier: Topic :: Software Development :: Libraries
Classifier: Topic :: Software Development :: Libraries :: Python Modules
Classifier: Topic :: System :: Software Distribution
Classifier: Topic :: Utilities
Classifier: Operating System :: MacOS
Classifier: Operating System :: Microsoft :: Windows
Classifier: Operating System :: POSIX :: Linux
Classifier: Programming Language :: Python :: 3.10
Classifier: Programming Language :: Python :: 3.11
Classifier: Programming Language :: Python :: 3.12
Classifier: Programming Language :: Python :: 3.13
Classifier: Programming Language :: Python :: 3.14
Classifier: Programming Language :: Python :: Implementation :: CPython
Requires-Python: !=2.*,>=3.10
Requires-Dist: setuptools
Requires-Dist: boltons>=25.0.0
Requires-Dist: cryptography>=41.0.0
Requires-Dist: docopt>=0.6.2
Requires-Dist: environs>=10.0.0
Requires-Dist: feedparser>=6.0.0
Requires-Dist: msgpack>=1.0.8
Requires-Dist: ntplib>=0.4.0
Requires-Dist: packaging>=22.0
Requires-Dist: psutil>=7.1.3
Requires-Dist: requests>=2.20.0
Requires-Dist: setuptools>=60.8.0
Requires-Dist: wheel>=0.38.1
Dynamic: author
Dynamic: author-email
Dynamic: classifier
Dynamic: description
Dynamic: description-content-type
Dynamic: home-page
Dynamic: keywords
Dynamic: license
Dynamic: project-url
Dynamic: requires-dist
Dynamic: requires-python
Dynamic: summary
